setup.py
src/ore/__init__.py
src/ore.viewlet.egg-info/PKG-INFO
src/ore.viewlet.egg-info/SOURCES.txt
src/ore.viewlet.egg-info/dependency_links.txt
src/ore.viewlet.egg-info/namespace_packages.txt
src/ore.viewlet.egg-info/not-zip-safe
src/ore.viewlet.egg-info/requires.txt
src/ore.viewlet.egg-info/top_level.txt
src/ore/viewlet/__init__.py
src/ore/viewlet/base.py
src/ore/viewlet/container.py
src/ore/viewlet/core.py
src/ore/viewlet/interfaces.py
src/ore/viewlet/manager.py
src/ore/viewlet/viewlet.py