Metadata-Version: 1.0
Name: ore.viewlet
Version: 0.2.1
Summary:     These are some extensions of the base zope.viewlet model, preconstructed
Home-page: UNKNOWN
Author: Kapil Thangavelu
Author-email: info@objectrealms.net
License: GPL
Keywords: zope zope3
Platform: UNKNOWN
